LICENSE
MANIFEST.in
README.md
pyproject.toml
setup.py
django_snart.egg-info/PKG-INFO
django_snart.egg-info/SOURCES.txt
django_snart.egg-info/dependency_links.txt
django_snart.egg-info/requires.txt
django_snart.egg-info/top_level.txt
snart/__init__.py
snart/admin.py
snart/apps.py
snart/filters.py
snart/translation.py
snart/management/__init__.py
snart/management/commands/__init__.py
snart/management/commands/discover_snarts.py
snart/migrations/0001_initial.py
snart/migrations/__init__.py
snart/models/__init__.py
snart/models/constant.py
snart/static/snart/css/style.css
snart/static/snart/js/jquery-ui.min.js
snart/templatetags/__init__.py
snart/templatetags/snart.py