Metadata-Version: 2.1
Name: django-snart
Version: 0.0.1
Summary: A Django app for text translation of non-model content
Home-page: https://github.com/stopdesign/django-snart
Author: Gregory Zhizhilkin
Author-email: Gregory Zhizhilkin <gregory@stopdesign.ru>
License: MIT License
Project-URL: Homepage, https://github.com/stopdesign/django-snart
Requires-Python: >=3.10
License-File: LICENSE
Requires-Dist: django-modeltranslation
Provides-Extra: dev
Requires-Dist: requests; extra == "dev"
